{
    "Contents": [
        {
            "Key": "Establishing Jesus Ancestry1.mp3",
            "LastModified": "2025-04-07T13:35:08.749000+00:00",
            "ETag": "\"ecfd6fa48f36c821e539df1c43c51e33\"",
            "Size": 2214572,
            "StorageClass": "STANDARD"
        },
        {
            "Key": "Event - Baptism of Jesus in the Jordan.mp3",
            "LastModified": "2025-04-07T13:35:08.657000+00:00",
            "ETag": "\"e76e45f53d70e77c371b5f2845d76993\"",
            "Size": 2213132,
            "StorageClass": "STANDARD"
        },
        {
            "Key": "Event - Bestowal of the Spirit of Truth.mp3",
            "LastModified": "2025-04-07T13:35:08.875000+00:00",
            "ETag": "\"6563ccd543cff91f9b35964d71daca17\"",
            "Size": 3651308,
            "StorageClass": "STANDARD"
        },
        {
            "Key": "Event - Betrayal and Arrest of Jesus.mp3",
            "LastModified": "2025-04-07T13:35:08.829000+00:00",
            "ETag": "\"4fdb8c61c658bd8d561c2fe4c5343897\"",
            "Size": 2645132,
            "StorageClass": "STANDARD"
        },
        {
            "Key": "Event - Birth and Infancy of Jesus.mp3",
            "LastModified": "2025-04-07T13:35:09.024000+00:00",
            "ETag": "\"1b487f16f8709fd2fca09e43a59ac296\"",
            "Size": 3424652,
            "StorageClass": "STANDARD"
        },
        {
            "Key": "Event - Conference with John_s Apostles.mp3",
            "LastModified": "2025-04-07T13:35:10.702000+00:00",
            "ETag": "\"e777538bba52812d1c3f36f00eb26708\"",
            "Size": 3321452,
            "StorageClass": "STANDARD"
        },
        {
            "Key": "Event - First Preaching Tour of Galilee.mp3",
            "LastModified": "2025-04-07T13:35:10.844000+00:00",
            "ETag": "\"9e75c732872b0b269198911aad736a44\"",
            "Size": 3174860,
            "StorageClass": "STANDARD"
        },
        {
            "Key": "Event - Forty Days in the Wilderness.mp3",
            "LastModified": "2025-04-07T13:35:10.898000+00:00",
            "ETag": "\"f52b4b8526de12dc79725d66c0f39fc2\"",
            "Size": 2725772,
            "StorageClass": "STANDARD"
        },
        {
            "Key": "Event - Jesus Alone in Gethsemane.mp3",
            "LastModified": "2025-04-07T13:35:10.337000+00:00",
            "ETag": "\"b06728c5fae9a9688bfa627b5f8a1b05\"",
            "Size": 2040908,
            "StorageClass": "STANDARD"
        },
        {
            "Key": "Event - Jesus Attends a Wedding at Cana.mp3",
            "LastModified": "2025-04-07T13:35:10.628000+00:00",
            "ETag": "\"4ee139389385b3ffabb04eddb2d859d8\"",
            "Size": 1851980,
            "StorageClass": "STANDARD"
        },
        {
            "Key": "Event - Jesus Cleanses the Temple of Moneylenders.mp3",
            "LastModified": "2025-04-07T13:35:11.757000+00:00",
            "ETag": "\"58b402bcf397a252e1b903d714928dd2\"",
            "Size": 3139340,
            "StorageClass": "STANDARD"
        },
        {
            "Key": "Event - Jesus Establishes the Women_s Corps.mp3",
            "LastModified": "2025-04-07T13:35:12.363000+00:00",
            "ETag": "\"ae11e8d14ce15a3b386c6bdd80fec9f0\"",
            "Size": 2744012,
            "StorageClass": "STANDARD"
        },
        {
            "Key": "Event - Jesus Feeds the Five Thousand.mp3",
            "LastModified": "2025-04-07T13:35:12.179000+00:00",
            "ETag": "\"04fe2c90afe1335559ba0c4d3a02dbb4\"",
            "Size": 2328140,
            "StorageClass": "STANDARD"
        },
        {
            "Key": "Event - Jesus Ordains His Twelve Apostles.mp3",
            "LastModified": "2025-04-07T13:35:12.623000+00:00",
            "ETag": "\"135ccfa1cc03b9a9c8ade6827a70002c\"",
            "Size": 3634028,
            "StorageClass": "STANDARD"
        },
        {
            "Key": "Event - Jesus_ Discourse on True Religion.mp3",
            "LastModified": "2025-04-07T13:35:12.668000+00:00",
            "ETag": "\"98ca99008f7131ae58387dc53274bd66\"",
            "Size": 3619052,
            "StorageClass": "STANDARD"
        },
        {
            "Key": "Event - Jesus_ Entry into Jerusalem - Palm Sunday.mp3",
            "LastModified": "2025-04-07T13:35:13.009000+00:00",
            "ETag": "\"4622b6d2badb71e59c2b4902bfba015f\"",
            "Size": 1770092,
            "StorageClass": "STANDARD"
        },
        {
            "Key": "Event - Jesus_ First Passover - Age 13.mp3",
            "LastModified": "2025-04-07T13:35:13.330000+00:00",
            "ETag": "\"c2e902fab6e5d4ea09f05fa281597354\"",
            "Size": 2190572,
            "StorageClass": "STANDARD"
        },
        {
            "Key": "Event - Peter Denies Jesus Three Times.mp3",
            "LastModified": "2025-04-07T13:35:13.695000+00:00",
            "ETag": "\"1e98014e8cc502ecb2545f6bb241707a\"",
            "Size": 2610572,
            "StorageClass": "STANDARD"
        },
        {
            "Key": "Event - Pilate_s Last Appeal and Surrender.mp3",
            "LastModified": "2025-04-07T13:35:13.885000+00:00",
            "ETag": "\"25f98e1d5151950856fecaa7d758995f\"",
            "Size": 2281100,
            "StorageClass": "STANDARD"
        },
        {
            "Key": "Event - Resurrection of Lazarus.mp3",
            "LastModified": "2025-04-07T13:35:13.825000+00:00",
            "ETag": "\"984610a86b0731111a579afc4505f4c0\"",
            "Size": 1920812,
            "StorageClass": "STANDARD"
        },
        {
            "Key": "Event - Sojourn in Alexandria.mp3",
            "LastModified": "2025-04-07T13:35:14.313000+00:00",
            "ETag": "\"af75e3965e50fe747f43e6a9b1f213de\"",
            "Size": 2845580,
            "StorageClass": "STANDARD"
        },
        {
            "Key": "Event - The Feast of Tabernacles.mp3",
            "LastModified": "2025-04-07T13:35:14.647000+00:00",
            "ETag": "\"971650ef27c6b830a2f2c218fecc623a\"",
            "Size": 2306732,
            "StorageClass": "STANDARD"
        },
        {
            "Key": "Event - The Great Temptation.mp3",
            "LastModified": "2025-04-07T13:35:15.319000+00:00",
            "ETag": "\"ed8b6c4b5767bfee76f9fb629b97c96a\"",
            "Size": 2759660,
            "StorageClass": "STANDARD"
        },
        {
            "Key": "Event - The Healing at Sundown.mp3",
            "LastModified": "2025-04-07T13:35:14.922000+00:00",
            "ETag": "\"39831da05e0441382001f9f39889ce8b\"",
            "Size": 1511468,
            "StorageClass": "STANDARD"
        },
        {
            "Key": "Event - The King-Making Episode.mp3",
            "LastModified": "2025-04-07T13:35:28.562000+00:00",
            "ETag": "\"162ee943957449828a386f0329d62c66\"",
            "Size": 1916012,
            "StorageClass": "STANDARD"
        },
        {
            "Key": "Event - The Last Supper.mp3",
            "LastModified": "2025-04-07T13:35:29.083000+00:00",
            "ETag": "\"6f39540cedfa1be2fa8dd9cafbbdd09e\"",
            "Size": 3825452,
            "StorageClass": "STANDARD"
        },
        {
            "Key": "Event - The Resurrection of Jesus.mp3",
            "LastModified": "2025-04-07T13:35:28.930000+00:00",
            "ETag": "\"73a446395d514e4eb1efaea8dbfc0f08\"",
            "Size": 3080972,
            "StorageClass": "STANDARD"
        },
        {
            "Key": "Event - The Second Preaching Tour.mp3",
            "LastModified": "2025-04-07T13:35:29.105000+00:00",
            "ETag": "\"c81dba2a6f83e9f32a06b3aaec77d1a3\"",
            "Size": 2907500,
            "StorageClass": "STANDARD"
        },
        {
            "Key": "Event - The Transfiguration.mp3",
            "LastModified": "2025-04-07T13:35:28.769000+00:00",
            "ETag": "\"0a0c6ecbf49cfd3aaede9d3dc3e3d4fd\"",
            "Size": 2423372,
            "StorageClass": "STANDARD"
        },
        {
            "Key": "Group - Gentiles.mp3",
            "LastModified": "2025-04-07T13:35:29.837000+00:00",
            "ETag": "\"4600bccf0a15555d020ec40097974135\"",
            "Size": 2325260,
            "StorageClass": "STANDARD"
        },
        {
            "Key": "Group - Jesus_ Siblings.mp3",
            "LastModified": "2025-04-07T13:35:30.867000+00:00",
            "ETag": "\"96a1ad8049fc6e6161b4b71a424aa807\"",
            "Size": 3022412,
            "StorageClass": "STANDARD"
        },
        {
            "Key": "Group - Lazarus, Martha, and Mary of Bethany.mp3",
            "LastModified": "2025-04-07T13:35:30.237000+00:00",
            "ETag": "\"ffef38d1091d056dd7dfdead148d3f05\"",
            "Size": 2922188,
            "StorageClass": "STANDARD"
        },
        {
            "Key": "Group - Pharisees.mp3",
            "LastModified": "2025-04-07T13:35:30.769000+00:00",
            "ETag": "\"73344068e34c67ae77d02a2b8034bc03\"",
            "Size": 2953100,
            "StorageClass": "STANDARD"
        },
        {
            "Key": "Group - Sadducees.mp3",
            "LastModified": "2025-04-07T13:35:30.780000+00:00",
            "ETag": "\"5f324e50fe80b6e851a6d97c945e1f9f\"",
            "Size": 2669900,
            "StorageClass": "STANDARD"
        },
        {
            "Key": "Group - Samaritans.mp3",
            "LastModified": "2025-04-07T13:35:31.066000+00:00",
            "ETag": "\"532d38d46d4998d4d3c7c40fdfcfc0b9\"",
            "Size": 2600780,
            "StorageClass": "STANDARD"
        },
        {
            "Key": "Group - Sanhedrin.mp3",
            "LastModified": "2025-04-07T13:35:31.445000+00:00",
            "ETag": "\"75679ba2a339f9348fbb43575f2701e4\"",
            "Size": 2912492,
            "StorageClass": "STANDARD"
        },
        {
            "Key": "Group - Seventy Disciples.mp3",
            "LastModified": "2025-04-07T13:35:32.004000+00:00",
            "ETag": "\"d997a9ba519adb56dc6710051526afc9\"",
            "Size": 1565612,
            "StorageClass": "STANDARD"
        },
        {
            "Key": "Group - Six Jerusalem Spies.mp3",
            "LastModified": "2025-04-07T13:35:32.272000+00:00",
            "ETag": "\"68befbc99a99afe9c67b4fc3a87f0d64\"",
            "Size": 2235212,
            "StorageClass": "STANDARD"
        },
        {
            "Key": "Group - The Twelve Apostles.mp3",
            "LastModified": "2025-04-07T13:35:32.199000+00:00",
            "ETag": "\"5bdec6b5e67553149f7a9498a5bf52d2\"",
            "Size": 3154892,
            "StorageClass": "STANDARD"
        },
        {
            "Key": "Group - The Twelve Apostles1.mp3",
            "LastModified": "2025-04-07T13:35:32.507000+00:00",
            "ETag": "\"82148ba41e985099da1656abf72ecf30\"",
            "Size": 2879948,
            "StorageClass": "STANDARD"
        },
        {
            "Key": "Group - Three Wise Men.mp3",
            "LastModified": "2025-04-07T13:35:32.607000+00:00",
            "ETag": "\"b62738bbd63d4459dcc74adfc74f2d8a\"",
            "Size": 2198060,
            "StorageClass": "STANDARD"
        },
        {
            "Key": "Group - Women_s Evangelistic Corps.mp3",
            "LastModified": "2025-04-07T13:35:33.133000+00:00",
            "ETag": "\"bfa16278dae84709b9b449fb38c3683a\"",
            "Size": 2144588,
            "StorageClass": "STANDARD"
        },
        {
            "Key": "Group - Zealots.mp3",
            "LastModified": "2025-04-07T13:35:33.291000+00:00",
            "ETag": "\"1cd53cdcc38c9451048dc5e177581430\"",
            "Size": 1825292,
            "StorageClass": "STANDARD"
        },
        {
            "Key": "Group - Zebedee_s Family.mp3",
            "LastModified": "2025-04-07T13:35:33.322000+00:00",
            "ETag": "\"d96fb02e0fad88f75a1aca5f25e3ebaf\"",
            "Size": 1343852,
            "StorageClass": "STANDARD"
        },
        {
            "Key": "Object - Home of Jesus in Nazareth.mp3",
            "LastModified": "2025-04-07T13:35:33.614000+00:00",
            "ETag": "\"0f8f8cc8956b5dfe29351093b2ed022c\"",
            "Size": 2394188,
            "StorageClass": "STANDARD"
        },
        {
            "Key": "Person - Abner.mp3",
            "LastModified": "2025-04-07T13:35:33.869000+00:00",
            "ETag": "\"2577d50819e5abcc428fa6965034de75\"",
            "Size": 2624012,
            "StorageClass": "STANDARD"
        },
        {
            "Key": "Person - Agaman.mp3",
            "LastModified": "2025-04-07T13:35:34.693000+00:00",
            "ETag": "\"002c575a1411b47bbb54de364427834c\"",
            "Size": 3323372,
            "StorageClass": "STANDARD"
        },
        {
            "Key": "Person - Andrew.mp3",
            "LastModified": "2025-04-07T13:35:35.068000+00:00",
            "ETag": "\"a336d6f11b72ec2caae715503bd5435f\"",
            "Size": 4054028,
            "StorageClass": "STANDARD"
        },
        {
            "Key": "Person - Caiaphas.mp3",
            "LastModified": "2025-04-07T13:35:34.592000+00:00",
            "ETag": "\"96d1d546ac29d62bcdcf5d9b1765aac3\"",
            "Size": 1856972,
            "StorageClass": "STANDARD"
        },
        {
            "Key": "Person - David Zebedee.mp3",
            "LastModified": "2025-04-07T13:35:54.814000+00:00",
            "ETag": "\"baf6f59f8a904adc56be27d3fbdb3236\"",
            "Size": 2506412,
            "StorageClass": "STANDARD"
        },
        {
            "Key": "Person - Elizabeth - mother of John the Baptist.mp3",
            "LastModified": "2025-04-07T13:35:54.848000+00:00",
            "ETag": "\"1991096ca4afff50450a4cf5c7d5fe7d\"",
            "Size": 3472652,
            "StorageClass": "STANDARD"
        },
        {
            "Key": "Person - Gabriel.mp3",
            "LastModified": "2025-04-07T13:35:54.761000+00:00",
            "ETag": "\"5818f01a21ce074c50274a6bd618dae7\"",
            "Size": 3403532,
            "StorageClass": "STANDARD"
        },
        {
            "Key": "Person - Gadiah.mp3",
            "LastModified": "2025-04-07T13:35:54.451000+00:00",
            "ETag": "\"98e26ce34c635baa3c12a60526562e1d\"",
            "Size": 1693772,
            "StorageClass": "STANDARD"
        },
        {
            "Key": "Person - Ganid.mp3",
            "LastModified": "2025-04-07T13:35:54.944000+00:00",
            "ETag": "\"4ca896703465185b3053bcd083cdb9a5\"",
            "Size": 2914700,
            "StorageClass": "STANDARD"
        },
        {
            "Key": "Person - Gonod.mp3",
            "LastModified": "2025-04-07T13:35:55.399000+00:00",
            "ETag": "\"ccd944aa1ad5cf6a4f95079fec7a0cd8\"",
            "Size": 2368460,
            "StorageClass": "STANDARD"
        },
        {
            "Key": "Person - Herod Antipas.mp3",
            "LastModified": "2025-04-07T13:35:56.680000+00:00",
            "ETag": "\"a8ea3043867fd47614236711f3331cc3\"",
            "Size": 3012620,
            "StorageClass": "STANDARD"
        },
        {
            "Key": "Person - James - brother of Jesus.mp3",
            "LastModified": "2025-04-07T13:35:56.553000+00:00",
            "ETag": "\"15accb633974c68f1ea6a8193c95f77e\"",
            "Size": 3140300,
            "StorageClass": "STANDARD"
        },
        {
            "Key": "Person - James Alpheus.mp3",
            "LastModified": "2025-04-07T13:35:56.571000+00:00",
            "ETag": "\"2cf433a2b2a2855a092fe4dae920fd7e\"",
            "Size": 2168588,
            "StorageClass": "STANDARD"
        },
        {
            "Key": "Person - James Zebedee.mp3",
            "LastModified": "2025-04-07T13:35:56.833000+00:00",
            "ETag": "\"3389714103781eb118ac27c43a6f765e\"",
            "Size": 2743148,
            "StorageClass": "STANDARD"
        },
        {
            "Key": "Person - Jesus.mp3",
            "LastModified": "2025-04-07T13:35:56.873000+00:00",
            "ETag": "\"577abfa0e374d6a6dccbf364684627b2\"",
            "Size": 2757932,
            "StorageClass": "STANDARD"
        },
        {
            "Key": "Person - Jesus1.mp3",
            "LastModified": "2025-04-07T13:35:58.038000+00:00",
            "ETag": "\"d6fc04ed2ffd5cb1c22ca33edfff7891\"",
            "Size": 2222252,
            "StorageClass": "STANDARD"
        },
        {
            "Key": "Person - John Mark.mp3",
            "LastModified": "2025-04-07T13:35:58.062000+00:00",
            "ETag": "\"dfba3b861fcb17e9ac251d8e14f24fcc\"",
            "Size": 2155052,
            "StorageClass": "STANDARD"
        },
        {
            "Key": "Person - John Zebedee.mp3",
            "LastModified": "2025-04-07T13:35:58.320000+00:00",
            "ETag": "\"abf68aa954a4af3b93b5d1db5757e8ca\"",
            "Size": 2227148,
            "StorageClass": "STANDARD"
        },
        {
            "Key": "Person - Joseph - brother of Jesus.mp3",
            "LastModified": "2025-04-07T13:35:58.243000+00:00",
            "ETag": "\"2f5d7fbd45a0cc961a528f5a1a6c15a3\"",
            "Size": 1777292,
            "StorageClass": "STANDARD"
        },
        {
            "Key": "Person - Joseph - father of Jesus.mp3",
            "LastModified": "2025-04-07T13:35:58.498000+00:00",
            "ETag": "\"edcd1b454bc70c6f4be14616967a8235\"",
            "Size": 3356108,
            "StorageClass": "STANDARD"
        },
        {
            "Key": "Person - Joseph of Arimathea.mp3",
            "LastModified": "2025-04-07T13:35:59.852000+00:00",
            "ETag": "\"2df21193b8da7adb7085e7cb3ad1c7d4\"",
            "Size": 2976428,
            "StorageClass": "STANDARD"
        },
        {
            "Key": "Person - Josiah.mp3",
            "LastModified": "2025-04-07T13:35:59.463000+00:00",
            "ETag": "\"64ecb08ebcc9867d2375df7150294991\"",
            "Size": 2332941,
            "StorageClass": "STANDARD"
        },
        {
            "Key": "Person - Judas Alpheus.mp3",
            "LastModified": "2025-04-07T13:36:00.055000+00:00",
            "ETag": "\"73dfd4a690a9dac70f11828a7634c384\"",
            "Size": 3440108,
            "StorageClass": "STANDARD"
        },
        {
            "Key": "Person - Judas Iscariot.mp3",
            "LastModified": "2025-04-07T13:35:59.693000+00:00",
            "ETag": "\"278518a9a216bcd50054aba24c51ab1d\"",
            "Size": 1533068,
            "StorageClass": "STANDARD"
        },
        {
            "Key": "Person - Jude - brother of Jesus.mp3",
            "LastModified": "2025-04-07T13:36:00.216000+00:00",
            "ETag": "\"8de1b6ef136dd7182065ee0fad118279\"",
            "Size": 2713100,
            "StorageClass": "STANDARD"
        },
        {
            "Key": "Person - Lazarus.mp3",
            "LastModified": "2025-04-07T13:36:00.707000+00:00",
            "ETag": "\"fe69700646bad5f773f6e3e56376529f\"",
            "Size": 2239052,
            "StorageClass": "STANDARD"
        },
        {
            "Key": "Person - Machiventa Melchizedek.mp3",
            "LastModified": "2025-04-07T13:36:01.045000+00:00",
            "ETag": "\"8288752815eaaac3aa095d4afb2c3137\"",
            "Size": 3028652,
            "StorageClass": "STANDARD"
        },
        {
            "Key": "Person - Martha - of Bethany.mp3",
            "LastModified": "2025-04-07T13:36:01.133000+00:00",
            "ETag": "\"8e64c87d44634382f55937c8b0bf0946\"",
            "Size": 1981772,
            "StorageClass": "STANDARD"
        },
        {
            "Key": "Person - Mary - mother of Jesus.mp3",
            "LastModified": "2025-04-07T13:36:01.146000+00:00",
            "ETag": "\"da7b4dca823f82301a3362f80f570f43\"",
            "Size": 2372492,
            "StorageClass": "STANDARD"
        },
        {
            "Key": "Person - Mary - of Bethany.mp3",
            "LastModified": "2025-04-07T13:36:20.003000+00:00",
            "ETag": "\"c75c4842277e3e3adda0a4f4a7050460\"",
            "Size": 2879660,
            "StorageClass": "STANDARD"
        },
        {
            "Key": "Person - Mary - wife of Elijah Mark.mp3",
            "LastModified": "2025-04-07T13:36:19.607000+00:00",
            "ETag": "\"2d33eea2f2fb0710aa04cbeaeca1ca43\"",
            "Size": 1735340,
            "StorageClass": "STANDARD"
        },
        {
            "Key": "Person - Mary Magdalene.mp3",
            "LastModified": "2025-04-07T13:36:20.012000+00:00",
            "ETag": "\"dbc9961bf0fd1740669117a2373d1fc4\"",
            "Size": 2841932,
            "StorageClass": "STANDARD"
        },
        {
            "Key": "Person - Mary Magdalene1.mp3",
            "LastModified": "2025-04-07T13:36:19.796000+00:00",
            "ETag": "\"fdffef22645b3676cc9f6e8975c780c8\"",
            "Size": 2355213,
            "StorageClass": "STANDARD"
        },
        {
            "Key": "Person - Matthew Levi.mp3",
            "LastModified": "2025-04-07T13:36:19.888000+00:00",
            "ETag": "\"aa65e6c453fac5aaf620c287b0d5ab00\"",
            "Size": 2531852,
            "StorageClass": "STANDARD"
        },
        {
            "Key": "Person - Miriam.mp3",
            "LastModified": "2025-04-07T13:36:20.728000+00:00",
            "ETag": "\"b936a7f449ec624e417821674de26cd3\"",
            "Size": 1864460,
            "StorageClass": "STANDARD"
        },
        {
            "Key": "Person - Nathaniel.mp3",
            "LastModified": "2025-04-07T13:36:21.451000+00:00",
            "ETag": "\"ccd03fd6efa5f2dfade1a8c3be6d70df\"",
            "Size": 3346220,
            "StorageClass": "STANDARD"
        },
        {
            "Key": "Person - Paul.mp3",
            "LastModified": "2025-04-07T13:36:21.448000+00:00",
            "ETag": "\"e5177ef54c9c1f7ecda6307a3e23d6b9\"",
            "Size": 2993612,
            "StorageClass": "STANDARD"
        },
        {
            "Key": "Person - Philip - apostle of Jesus.mp3",
            "LastModified": "2025-04-07T13:36:21.558000+00:00",
            "ETag": "\"480a92e4789beee2e673233591b43806\"",
            "Size": 2259980,
            "StorageClass": "STANDARD"
        },
        {
            "Key": "Person - Rebecca - of Sepphoris.mp3",
            "LastModified": "2025-04-07T13:36:21.820000+00:00",
            "ETag": "\"50413c9c9defc2563c2c68d4df9dbaec\"",
            "Size": 4037900,
            "StorageClass": "STANDARD"
        },
        {
            "Key": "Person - Rodan.mp3",
            "LastModified": "2025-04-07T13:36:21.916000+00:00",
            "ETag": "\"9251640d8400f5e218345c5738472204\"",
            "Size": 2737580,
            "StorageClass": "STANDARD"
        },
        {
            "Key": "Person - Ruth - sister of Jesus.mp3",
            "LastModified": "2025-04-07T13:36:23.357000+00:00",
            "ETag": "\"222344d78134a5354b6fc61cffbbe652\"",
            "Size": 3068108,
            "StorageClass": "STANDARD"
        },
        {
            "Key": "Person - Salome - wife of Zebedee.mp3",
            "LastModified": "2025-04-07T13:36:23.372000+00:00",
            "ETag": "\"a45ea2783d743b6cb07b887a98d81712\"",
            "Size": 2551340,
            "StorageClass": "STANDARD"
        },
        {
            "Key": "Person - Satan.mp3",
            "LastModified": "2025-04-07T13:36:23.185000+00:00",
            "ETag": "\"86cc153712d744907b069519e9ea6b53\"",
            "Size": 2458700,
            "StorageClass": "STANDARD"
        },
        {
            "Key": "Person - Simon - brother of Jesus.mp3",
            "LastModified": "2025-04-07T13:36:23.368000+00:00",
            "ETag": "\"d0dde371911dfba1a0a6640562bd7a29\"",
            "Size": 1711820,
            "StorageClass": "STANDARD"
        },
        {
            "Key": "Person - Simon Peter.mp3",
            "LastModified": "2025-04-07T13:36:23.334000+00:00",
            "ETag": "\"a15a9356cec9002875b301183068996c\"",
            "Size": 2222540,
            "StorageClass": "STANDARD"
        },
        {
            "Key": "Person - Simon Zelotes.mp3",
            "LastModified": "2025-04-07T13:36:24.768000+00:00",
            "ETag": "\"4e3457b2fb844a63e92ca13c6fb04816\"",
            "Size": 2586572,
            "StorageClass": "STANDARD"
        },
        {
            "Key": "Person - Stephen.mp3",
            "LastModified": "2025-04-07T13:36:25.035000+00:00",
            "ETag": "\"5487f06c2956a48947a4dad21c4ec463\"",
            "Size": 2263052,
            "StorageClass": "STANDARD"
        },
        {
            "Key": "Person - Thomas Didymus.mp3",
            "LastModified": "2025-04-07T13:36:25.490000+00:00",
            "ETag": "\"0b8ff2eebd5b1f0f4bfe904b229ccb7f\"",
            "Size": 2803820,
            "StorageClass": "STANDARD"
        },
        {
            "Key": "Person - Zebedee.mp3",
            "LastModified": "2025-04-07T13:36:25.213000+00:00",
            "ETag": "\"5573077fdd26156602882ac0088d2e2c\"",
            "Size": 3150092,
            "StorageClass": "STANDARD"
        },
        {
            "Key": "Relationship - Jesus-James (Brother of Jesus).mp3",
            "LastModified": "2025-04-07T13:36:25.332000+00:00",
            "ETag": "\"d936b723e0dfea1cd9ac9a7d33c2494f\"",
            "Size": 3111020,
            "StorageClass": "STANDARD"
        },
        {
            "Key": "Relationship - Jesus-Judas Iscariot.mp3",
            "LastModified": "2025-04-07T13:36:25.983000+00:00",
            "ETag": "\"eb3e983185dfc9b8d61c9322b84c418b\"",
            "Size": 1839212,
            "StorageClass": "STANDARD"
        },
        {
            "Key": "Topic - Accidents and Divine Intervention.mp3",
            "LastModified": "2025-04-07T13:36:26.094000+00:00",
            "ETag": "\"4e072db7ee3f1e097b8304620aab5ada\"",
            "Size": 1736492,
            "StorageClass": "STANDARD"
        },
        {
            "Key": "Topic - Acme of Religious Living.mp3",
            "LastModified": "2025-04-07T13:36:26.618000+00:00",
            "ETag": "\"b9bc7efbe790867cb3f5128eb542ca26\"",
            "Size": 3337868,
            "StorageClass": "STANDARD"
        },
        {
            "Key": "Topic - After Pentecost - Peter, Paul, and Christianity.mp3",
            "LastModified": "2025-04-07T13:36:26.546000+00:00",
            "ETag": "\"5907e0fcb08bd84063807e2ebeacbeba\"",
            "Size": 1782380,
            "StorageClass": "STANDARD"
        },
        {
            "Key": "Topic - Angels - the Daughters of God.mp3",
            "LastModified": "2025-04-07T13:36:26.833000+00:00",
            "ETag": "\"45b41fb6f3d9ba69e05c4d80ff652bb2\"",
            "Size": 2677388,
            "StorageClass": "STANDARD"
        },
        {
            "Key": "Topic - Anger - The Lack of Understanding.mp3",
            "LastModified": "2025-04-07T13:36:49.561000+00:00",
            "ETag": "\"53738f1987b2f4251efddf4576ce9344\"",
            "Size": 3152780,
            "StorageClass": "STANDARD"
        },
        {
            "Key": "Topic - Art of Living.mp3",
            "LastModified": "2025-04-07T13:36:49.175000+00:00",
            "ETag": "\"0d4d6e3ab53a040c762233e2e506f80b\"",
            "Size": 1668140,
            "StorageClass": "STANDARD"
        },
        {
            "Key": "Topic - Balance and Lures of Maturity.mp3",
            "LastModified": "2025-04-07T13:36:49.481000+00:00",
            "ETag": "\"817cb230121dc75308bf69116cb02346\"",
            "Size": 2614988,
            "StorageClass": "STANDARD"
        },
        {
            "Key": "Topic - Concepts of the Expected Messiah.mp3",
            "LastModified": "2025-04-07T13:36:49.193000+00:00",
            "ETag": "\"af690bfce3ce1e855fc7fa82ea8dd85b\"",
            "Size": 2066540,
            "StorageClass": "STANDARD"
        },
        {
            "Key": "Topic - Did Jesus Ever Feel Sad.mp3",
            "LastModified": "2025-04-07T13:36:49.621000+00:00",
            "ETag": "\"a7c9a41c4cced918f33ea811bd359d2a\"",
            "Size": 2726732,
            "StorageClass": "STANDARD"
        },
        {
            "Key": "Topic - Did Jesus Marry Anyone.mp3",
            "LastModified": "2025-04-07T13:36:50.410000+00:00",
            "ETag": "\"5a16b494dd98269764e95ac1b7a84146\"",
            "Size": 1756460,
            "StorageClass": "STANDARD"
        },
        {
            "Key": "Topic - Divine Forgiveness.mp3",
            "LastModified": "2025-04-07T13:36:50.841000+00:00",
            "ETag": "\"4afee3b468e48adc02c59a84faf69164\"",
            "Size": 3002348,
            "StorageClass": "STANDARD"
        },
        {
            "Key": "Topic - Establishing Jesus Ancestry.mp3",
            "LastModified": "2025-04-07T13:36:51.066000+00:00",
            "ETag": "\"f30487e30d3879b3b438743443c0dda9\"",
            "Size": 2139500,
            "StorageClass": "STANDARD"
        },
        {
            "Key": "Topic - Evolution of the Atonement Doctrine.mp3",
            "LastModified": "2025-04-07T13:36:51.182000+00:00",
            "ETag": "\"760b0094d569b102932e8837b45cfd29\"",
            "Size": 1919468,
            "StorageClass": "STANDARD"
        },
        {
            "Key": "Topic - Faith and Righteousness.mp3",
            "LastModified": "2025-04-07T13:36:51.466000+00:00",
            "ETag": "\"176ac3a686f99d752d6c1bb7e5920857\"",
            "Size": 2928428,
            "StorageClass": "STANDARD"
        },
        {
            "Key": "Topic - Fatherly and Brotherly Love.mp3",
            "LastModified": "2025-04-07T13:36:52.052000+00:00",
            "ETag": "\"7353089b6f1876e9cf9f99f33c93f241\"",
            "Size": 2148428,
            "StorageClass": "STANDARD"
        },
        {
            "Key": "Topic - Good and Evil.mp3",
            "LastModified": "2025-04-07T13:36:52.141000+00:00",
            "ETag": "\"ea07713493af6f96e84961a0f53ad051\"",
            "Size": 2729132,
            "StorageClass": "STANDARD"
        },
        {
            "Key": "Topic - Growth of the God Concept.mp3",
            "LastModified": "2025-04-07T13:36:52.448000+00:00",
            "ETag": "\"6ae17a7978f8cedd77496092b05c9998\"",
            "Size": 2489420,
            "StorageClass": "STANDARD"
        },
        {
            "Key": "Topic - History of Baptism.mp3",
            "LastModified": "2025-04-07T13:36:52.352000+00:00",
            "ETag": "\"4d7ee771fdeae217c9cde2a4f3c8ee1b\"",
            "Size": 1532972,
            "StorageClass": "STANDARD"
        },
        {
            "Key": "Topic - Hobbies and Interests Jesus Enjoyed.mp3",
            "LastModified": "2025-04-07T13:36:52.727000+00:00",
            "ETag": "\"a247972794ca35fa6f416df39aa7e0b8\"",
            "Size": 2333708,
            "StorageClass": "STANDARD"
        },
        {
            "Key": "Topic - How Did Jesus Treat Women.mp3",
            "LastModified": "2025-04-07T13:36:53.415000+00:00",
            "ETag": "\"93ad4601b3a84e0a4d555753048d74f1\"",
            "Size": 1699628,
            "StorageClass": "STANDARD"
        },
        {
            "Key": "Topic - Importance of the Early Home Life.mp3",
            "LastModified": "2025-04-07T13:36:53.514000+00:00",
            "ETag": "\"736566e584757c83fc58ade0219d9d28\"",
            "Size": 2651852,
            "StorageClass": "STANDARD"
        },
        {
            "Key": "Topic - Indwelling Spirit of God.mp3",
            "LastModified": "2025-04-07T13:36:53.914000+00:00",
            "ETag": "\"290755ac75e8ec3c7d935003b22e67f1\"",
            "Size": 2056748,
            "StorageClass": "STANDARD"
        },
        {
            "Key": "Topic - Influence and Rule of the Roman Empire.mp3",
            "LastModified": "2025-04-07T13:36:54.181000+00:00",
            "ETag": "\"c03bffd1db29b56432d6742e8641b45d\"",
            "Size": 3312428,
            "StorageClass": "STANDARD"
        },
        {
            "Key": "Topic - Is Jesus_ Death Related to the Jewish Passover.mp3",
            "LastModified": "2025-04-07T13:36:54.508000+00:00",
            "ETag": "\"2906dce8b184ca2ee7add66eb47262dc\"",
            "Size": 2360877,
            "StorageClass": "STANDARD"
        },
        {
            "Key": "Topic - Jesus - Celestial Visitations.mp3",
            "LastModified": "2025-04-07T13:36:54.509000+00:00",
            "ETag": "\"98646e8977b54c124c64772ecb6c410e\"",
            "Size": 2262380,
            "StorageClass": "STANDARD"
        },
        {
            "Key": "Topic - Jesus - Human Rights Advocate.mp3",
            "LastModified": "2025-04-07T13:36:55.211000+00:00",
            "ETag": "\"25f00499a4144211ecb145c2254daa08\"",
            "Size": 2078540,
            "StorageClass": "STANDARD"
        },
        {
            "Key": "Topic - Jesus Bestowal Mission.mp3",
            "LastModified": "2025-04-07T13:36:55.150000+00:00",
            "ETag": "\"0d6b177d8ac7531cc53e1fb158bbc51b\"",
            "Size": 2477900,
            "StorageClass": "STANDARD"
        },
        {
            "Key": "Topic - Jesus Burial Cloths.mp3",
            "LastModified": "2025-04-07T13:36:55.610000+00:00",
            "ETag": "\"edb4741d4060b483098f46dcf2001e40\"",
            "Size": 2646572,
            "StorageClass": "STANDARD"
        },
        {
            "Key": "Topic - Jesus Christ - Our Creator Son.mp3",
            "LastModified": "2025-04-07T13:36:55.857000+00:00",
            "ETag": "\"cdf1b6435229b0681d59a1dcff0b8a26\"",
            "Size": 2196428,
            "StorageClass": "STANDARD"
        },
        {
            "Key": "Topic - Jesus Combined Nature.mp3",
            "LastModified": "2025-04-07T13:36:56.001000+00:00",
            "ETag": "\"e49d8508160e630a303861abb6cf0da3\"",
            "Size": 2297900,
            "StorageClass": "STANDARD"
        },
        {
            "Key": "Topic - Jesus First Year of Ministry.mp3",
            "LastModified": "2025-04-07T13:37:29.852000+00:00",
            "ETag": "\"2a8e6339051a8dc1419a25d702152cab\"",
            "Size": 2500554,
            "StorageClass": "STANDARD"
        },
        {
            "Key": "Topic - Jesus Harp.mp3",
            "LastModified": "2025-04-07T13:37:29.596000+00:00",
            "ETag": "\"4b02746e030fef2c1f76ca96de00a7ce\"",
            "Size": 1981866,
            "StorageClass": "STANDARD"
        },
        {
            "Key": "Topic - Jesus Miracles.mp3",
            "LastModified": "2025-04-07T13:37:29.998000+00:00",
            "ETag": "\"c42c17c90187f6dc583e3ac60447c9af\"",
            "Size": 2817548,
            "StorageClass": "STANDARD"
        },
        {
            "Key": "Topic - Jesus Parables.mp3",
            "LastModified": "2025-04-07T13:37:31.511000+00:00",
            "ETag": "\"e27827b76c88ef3d6caa5dca9a6b6a02\"",
            "Size": 14137291,
            "StorageClass": "STANDARD"
        },
        {
            "Key": "Topic - Jesus Personal Ministry as He Passed By.mp3",
            "LastModified": "2025-04-07T13:37:30.168000+00:00",
            "ETag": "\"749c427eb0ceba95d33be48364861c1a\"",
            "Size": 3472074,
            "StorageClass": "STANDARD"
        },
        {
            "Key": "Topic - Jesus Personalized Indwelling Spirit.mp3",
            "LastModified": "2025-04-07T13:37:31.318000+00:00",
            "ETag": "\"dc426a3eb4c010eac67816fddcf5e3b5\"",
            "Size": 2909228,
            "StorageClass": "STANDARD"
        },
        {
            "Key": "Topic - Jesus Return - Second Coming.mp3",
            "LastModified": "2025-04-07T13:37:31.674000+00:00",
            "ETag": "\"e36a358a03457372f942687661b297c6\"",
            "Size": 3254828,
            "StorageClass": "STANDARD"
        },
        {
            "Key": "Topic - Jesus_ Post-Resurrection Appearances.mp3",
            "LastModified": "2025-04-07T13:37:31.526000+00:00",
            "ETag": "\"fdfb4db6e03d9e0d965de144643493b6\"",
            "Size": 1668140,
            "StorageClass": "STANDARD"
        },
        {
            "Key": "Topic - Jesus_ Public Ministry.mp3",
            "LastModified": "2025-04-07T13:37:31.790000+00:00",
            "ETag": "\"7496099cb95af69457d7013afacccd56\"",
            "Size": 3690668,
            "StorageClass": "STANDARD"
        },
        {
            "Key": "Topic - Jesus_ Resurrected Morontia Body.mp3",
            "LastModified": "2025-04-07T13:37:32.750000+00:00",
            "ETag": "\"2953a6e3a9a2a998d7c2554f55194b61\"",
            "Size": 2738540,
            "StorageClass": "STANDARD"
        },
        {
            "Key": "Topic - Jesus_ Resurrection Experience.mp3",
            "LastModified": "2025-04-07T13:37:34.530000+00:00",
            "ETag": "\"de5e364575de2bf22c6dd66d15b9a5db\"",
            "Size": 10337611,
            "StorageClass": "STANDARD"
        },
        {
            "Key": "Topic - Jesus_ Tour of the Mediterranean World.mp3",
            "LastModified": "2025-04-07T13:37:33.807000+00:00",
            "ETag": "\"8636ea972fbc49128134b2025d91c56d\"",
            "Size": 2630732,
            "StorageClass": "STANDARD"
        },
        {
            "Key": "Topic - Life in First Century Palestine.mp3",
            "LastModified": "2025-04-07T13:37:33.930000+00:00",
            "ETag": "\"be8d02cfe54a9ac2fb2235096832a42e\"",
            "Size": 2652332,
            "StorageClass": "STANDARD"
        },
        {
            "Key": "Topic - Loving God Instead of Fearing God.mp3",
            "LastModified": "2025-04-07T13:37:34.097000+00:00",
            "ETag": "\"0b3fbaa5429ed3a207dbdbb8621d269a\"",
            "Size": 3068394,
            "StorageClass": "STANDARD"
        },
        {
            "Key": "Topic - Marriage, Divorce, and Children.mp3",
            "LastModified": "2025-04-07T13:37:34.398000+00:00",
            "ETag": "\"0688dceb333b8437368558366f6f74f3\"",
            "Size": 2559308,
            "StorageClass": "STANDARD"
        },
        {
            "Key": "Topic - Meaning of Jesus Death on the Cross.mp3",
            "LastModified": "2025-04-07T13:37:35.053000+00:00",
            "ETag": "\"0bb2d52b6c385706c065cb9c4e9289d3\"",
            "Size": 1445708,
            "StorageClass": "STANDARD"
        },
        {
            "Key": "Topic - Mistakes of Jesus_ Early Followers.mp3",
            "LastModified": "2025-04-07T13:37:38.408000+00:00",
            "ETag": "\"9b90185d3d99866c739fe25fc4afbaaa\"",
            "Size": 13884525,
            "StorageClass": "STANDARD"
        },
        {
            "Key": "Topic - Necessity for Jesus Departure.mp3",
            "LastModified": "2025-04-07T13:37:36.651000+00:00",
            "ETag": "\"01e24839e341aa500caed341223d3806\"",
            "Size": 2830508,
            "StorageClass": "STANDARD"
        },
        {
            "Key": "Topic - Overview of Jesus Teachings.mp3",
            "LastModified": "2025-04-07T13:37:37.234000+00:00",
            "ETag": "\"6bb8b7a5f3978802771f22b67aa079de\"",
            "Size": 5225997,
            "StorageClass": "STANDARD"
        },
        {
            "Key": "Topic - Personal Religion of Jesus.mp3",
            "LastModified": "2025-04-07T13:37:39.974000+00:00",
            "ETag": "\"d81778feec1f46d8538173b2162a413a\"",
            "Size": 17252685,
            "StorageClass": "STANDARD"
        },
        {
            "Key": "Topic - Philosophy - Materialism.mp3",
            "LastModified": "2025-04-07T13:37:37.126000+00:00",
            "ETag": "\"d5abde2144dbf52623f66be0e323f72f\"",
            "Size": 2431532,
            "StorageClass": "STANDARD"
        },
        {
            "Key": "Topic - Philosophy - Rodan of Alexandria.mp3",
            "LastModified": "2025-04-07T13:37:38.436000+00:00",
            "ETag": "\"c18b7ba3c925434c28ac2919abea8080\"",
            "Size": 2328332,
            "StorageClass": "STANDARD"
        },
        {
            "Key": "Topic - Philosophy - Secular Totalitarianism.mp3",
            "LastModified": "2025-04-07T13:37:38.925000+00:00",
            "ETag": "\"4c85387b7d58fe79e82e1ccd8e636896\"",
            "Size": 1957580,
            "StorageClass": "STANDARD"
        },
        {
            "Key": "Topic - Previous Written Records.mp3",
            "LastModified": "2025-04-07T13:37:39.465000+00:00",
            "ETag": "\"4b6c906d23cd39ee706e04cc590bc2b7\"",
            "Size": 3382892,
            "StorageClass": "STANDARD"
        },
        {
            "Key": "Topic - Profound Quotes to Live By.mp3",
            "LastModified": "2025-04-07T13:37:40.752000+00:00",
            "ETag": "\"e2f2b72d4d66792561ae49f9a2eec3fc\"",
            "Size": 4553420,
            "StorageClass": "STANDARD"
        },
        {
            "Key": "Topic - Religion - The Mystery Cults.mp3",
            "LastModified": "2025-04-07T13:37:40.395000+00:00",
            "ETag": "\"bdeb427b910d1b72ce4c59753e9ba7ca\"",
            "Size": 3817388,
            "StorageClass": "STANDARD"
        },
        {
            "Key": "Topic - Sonship with God.mp3",
            "LastModified": "2025-04-07T13:38:03.058000+00:00",
            "ETag": "\"9a05e39e072a97ed2936a503c8e9343d\"",
            "Size": 2703212,
            "StorageClass": "STANDARD"
        },
        {
            "Key": "Topic - Spirit of Truth - _The Comforter_.mp3",
            "LastModified": "2025-04-07T13:38:03.080000+00:00",
            "ETag": "\"57aaa3e76b1b14f57c9d33f518a1bd36\"",
            "Size": 2415692,
            "StorageClass": "STANDARD"
        },
        {
            "Key": "Topic - Star of Bethlehem.mp3",
            "LastModified": "2025-04-07T13:38:02.843000+00:00",
            "ETag": "\"1de1e3af0026c32f52cf962febaa7ee6\"",
            "Size": 1543052,
            "StorageClass": "STANDARD"
        },
        {
            "Key": "Topic - The Four Gospels.mp3",
            "LastModified": "2025-04-07T13:38:02.960000+00:00",
            "ETag": "\"fcf14fad18d3e43991371f07fcf1ea8d\"",
            "Size": 2261132,
            "StorageClass": "STANDARD"
        },
        {
            "Key": "Topic - The Kingdom of Heaven.mp3",
            "LastModified": "2025-04-07T13:38:03.026000+00:00",
            "ETag": "\"d4d8e42d1e759b96f9e661405a042b5c\"",
            "Size": 2257772,
            "StorageClass": "STANDARD"
        },
        {
            "Key": "Topic - The Paradise Trinity.mp3",
            "LastModified": "2025-04-07T13:38:04.163000+00:00",
            "ETag": "\"de12663dc0329389a740e959818bc842\"",
            "Size": 2475788,
            "StorageClass": "STANDARD"
        },
        {
            "Key": "Topic - The Personality of God.mp3",
            "LastModified": "2025-04-07T13:38:04.398000+00:00",
            "ETag": "\"8439fe92cdd02e28539a10bc9853070b\"",
            "Size": 2066828,
            "StorageClass": "STANDARD"
        },
        {
            "Key": "Topic - The Practical Power of Personal Faith.mp3",
            "LastModified": "2025-04-07T13:38:05.294000+00:00",
            "ETag": "\"0840343c3d85273aa63e0b76748049a8\"",
            "Size": 4041260,
            "StorageClass": "STANDARD"
        },
        {
            "Key": "Topic - The Two Thieves on the Cross.mp3",
            "LastModified": "2025-04-07T13:38:05.048000+00:00",
            "ETag": "\"25847f9889fc7572d6b66f2d63d9119c\"",
            "Size": 1959212,
            "StorageClass": "STANDARD"
        },
        {
            "Key": "Topic - The Western World in the First Century.mp3",
            "LastModified": "2025-04-07T13:38:05.573000+00:00",
            "ETag": "\"07c5fb97b7be4352a0809e6325fde508\"",
            "Size": 2824748,
            "StorageClass": "STANDARD"
        },
        {
            "Key": "Topic - Training the Kingdom_s Messengers.mp3",
            "LastModified": "2025-04-07T13:38:05.548000+00:00",
            "ETag": "\"3a4880148bd2a8afc7dc562cc9b1b24c\"",
            "Size": 2641100,
            "StorageClass": "STANDARD"
        },
        {
            "Key": "Topic - True Values.mp3",
            "LastModified": "2025-04-07T13:38:06.118000+00:00",
            "ETag": "\"f4e66b645d79fcd9690b9be1bf580f15\"",
            "Size": 1974572,
            "StorageClass": "STANDARD"
        },
        {
            "Key": "Topic - Was Jesus Really Born of a Virgin.mp3",
            "LastModified": "2025-04-07T13:38:06.850000+00:00",
            "ETag": "\"975a619bcc4949e04faac8b32d8a6ca2\"",
            "Size": 2596748,
            "StorageClass": "STANDARD"
        },
        {
            "Key": "Topic - What Did Jesus Say about Wealth.mp3",
            "LastModified": "2025-04-07T13:38:07.061000+00:00",
            "ETag": "\"713262c98ce032ff2e9529b4851c5ef7\"",
            "Size": 3109388,
            "StorageClass": "STANDARD"
        },
        {
            "Key": "Topic - What Happens When We Die.mp3",
            "LastModified": "2025-04-07T13:38:07.204000+00:00",
            "ETag": "\"4d106d4ce1623dde6468ac0546efdd93\"",
            "Size": 2134700,
            "StorageClass": "STANDARD"
        },
        {
            "Key": "Topic - What Is the Soul.mp3",
            "LastModified": "2025-04-07T13:38:07.706000+00:00",
            "ETag": "\"de6bfba248d01180c57d5289cacff564\"",
            "Size": 2295212,
            "StorageClass": "STANDARD"
        },
        {
            "Key": "Topic - What Is the Urantia Book.mp3",
            "LastModified": "2025-04-07T13:38:08.083000+00:00",
            "ETag": "\"cfbc12330b603a55c193147f641e140a\"",
            "Size": 3504908,
            "StorageClass": "STANDARD"
        },
        {
            "Key": "Topic - What Led Judas Iscariot to Betray Jesus.mp3",
            "LastModified": "2025-04-07T13:38:08.479000+00:00",
            "ETag": "\"e228f0af7806dce5862c18a7b58c2995\"",
            "Size": 2043020,
            "StorageClass": "STANDARD"
        },
        {
            "Key": "Topic - What Teaching Methods Did Jesus Use.mp3",
            "LastModified": "2025-04-07T13:38:08.802000+00:00",
            "ETag": "\"cb6d4f9b92592e02c11fc9cd337c46d9\"",
            "Size": 2145260,
            "StorageClass": "STANDARD"
        },
        {
            "Key": "Topic - When Was Jesus Born1.mp3",
            "LastModified": "2025-04-07T13:38:09.082000+00:00",
            "ETag": "\"195a871c660a966257e8eb453630cf83\"",
            "Size": 1659308,
            "StorageClass": "STANDARD"
        },
        {
            "Key": "Topic - Why Are Some People Happier than Others.mp3",
            "LastModified": "2025-04-07T13:38:09.661000+00:00",
            "ETag": "\"fbd6cae722ff851e36473d3ceace064a\"",
            "Size": 2413292,
            "StorageClass": "STANDARD"
        },
        {
            "Key": "Topic - Why Are We Confronted With Unfair Life Situations.mp3",
            "LastModified": "2025-04-07T13:38:09.899000+00:00",
            "ETag": "\"b9e0e313cd0a34b0ab66954efb80f6fd\"",
            "Size": 1686668,
            "StorageClass": "STANDARD"
        },
        {
            "Key": "Topic - Why Did Jesus Make a Triumphal Entry Into Jerusalem.mp3",
            "LastModified": "2025-04-07T13:38:10.407000+00:00",
            "ETag": "\"345ab4828da44419047318d0e091df13\"",
            "Size": 1743980,
            "StorageClass": "STANDARD"
        },
        {
            "Key": "Topic - Why Did the Sanhedrin Want Jesus_ Death.mp3",
            "LastModified": "2025-04-07T13:38:10.750000+00:00",
            "ETag": "\"be0ff92cc5c848d61ddcb8b091757a95\"",
            "Size": 1975052,
            "StorageClass": "STANDARD"
        },
        {
            "Key": "Topic - Why Do We Suffer from Affliction.mp3",
            "LastModified": "2025-04-07T13:38:11.149000+00:00",
            "ETag": "\"9a05ef32cd09a59926c68c0d858e4c77\"",
            "Size": 2518412,
            "StorageClass": "STANDARD"
        },
        {
            "Key": "Topic - Why Were Joseph and Mary Chosen as Jesus_ Parents.mp3",
            "LastModified": "2025-04-07T13:38:11.740000+00:00",
            "ETag": "\"cb3498965a1df8c60c59255962222f13\"",
            "Size": 2880332,
            "StorageClass": "STANDARD"
        },
        {
            "Key": "Topic - Worship and Prayer.mp3",
            "LastModified": "2025-04-07T13:38:27.238000+00:00",
            "ETag": "\"932017c809e1c91772dc7e4cdbaa7343\"",
            "Size": 2791148,
            "StorageClass": "STANDARD"
        }
    ],
    "RequestCharged": null,
    "Prefix": null
}
